{
    "goalTitle": "Mål",
    "goalText": "Mina mål är att utveckla mina kunskaper inom programmeringsbranchen genom att lära mig skriva kod av hög standard och lära mig mer om relaterade områden som kan hjälpa",
    "profileTitle": "Profil",
    "profileContent":[
        "Målmedveten person som strävar efter personlig utveckling.",
        "Tidigare erfarenhet av arbete inom IT",
        "Utbildning som .Net utvecklare"
    ],
    "personalTitle": "Personligt",
    "personalContent": "Jag bor i bromma. På min fritid gillar jag att promenera, laga mat och pyssla med småprojekt(ex bildredigering). Mina vänner beskriver mig som analytisk och en bra lyssnare"

}